approximate_cluster_identities/__init__.py
approximate_cluster_identities/__main__.py
approximate_cluster_identities-0.1.6.dist-info/LICENSE
approximate_cluster_identities-0.1.6.dist-info/METADATA
approximate_cluster_identities-0.1.6.dist-info/WHEEL
approximate_cluster_identities-0.1.6.dist-info/entry_points.txt
approximate_cluster_identities-0.1.6.dist-info/top_level.txt
approximate_cluster_identities-0.1.6.dist-info/RECORD
