Metadata-Version: 2.1
Name: approximate-cluster-identities
Version: 0.1.6
Summary: A package to calculate and visualise approximate cluster identities for a large number of short nucleotide sequences using minimizers.
Author: Daniel Anderson
Author-email: danp.anderson@outlook.com
Classifier: Development Status :: 3 - Alpha
Classifier: Intended Audience :: Science/Research
Classifier: Topic :: Scientific/Engineering :: Bio-Informatics
Classifier: License :: OSI Approved :: MIT License
Classifier: Programming Language :: Python :: 3.6
License-File: LICENSE
Requires-Dist: biopython
Requires-Dist: pandas
Requires-Dist: matplotlib
Requires-Dist: networkx
Requires-Dist: numpy
Requires-Dist: seaborn
Requires-Dist: sourmash
Requires-Dist: tqdm
Requires-Dist: joblib
